Workbook

Sheet Control de Vales
A1: ESTACIÓN DE SERVICIOS - REGISTRO Y CONTROL DE VALES DE CRÉDITO
B3: TOTAL VALES REGISTRADOS | E3: TOTAL DIESEL (GLN) | H3: TOTAL PREMIUM (GLN) | K3: IMPORTE TOTAL (S/.) | M3: VALES ANULADOS
B4: =COUNTA(E8:E100) | E4: =SUMIFS(J8:J100, I8:I100, "DIESEL B5", N8:N100, "<>ANULADO") | H4: =SUMIFS(J8:J100, I8:I100, "PREMIUM", N8:N100, "<>ANULADO") | K4: =SUMIF(N8:N100, "<>ANULADO", L8:L100) | M4: =COUNTIF(N8:N100, "ANULADO")
A7: ITEM | B7: FECHA EMISIÓN | C7: FECHA RECOJO | D7: TURNO | E7: N° VALE | F7: CLIENTE / EMPRESA | G7: PLACA | H7: CONDUCTOR | I7: PRODUCTO | J7: CANTIDAD (GLN) | K7: PRECIO (S/) | L7: TOTAL (S/) | M7: GRIFERO / ISLA | N7: ESTADO | O7: N° FACTURA / DOC
A8: 1 | B8: 2026-08-17 | C8: 2026-08-17 | D8: T1 | E8: 377 | F8: Transportes Andina S.A.C. | G8: A1B-823 | H8: Carlos Rojas | I8: PREMIUM | J8: 8 | K8: 19.5 | L8: =J8*K8 | M8: Juan P. | N8: FACTURADO | O8: F001-00452
A9: 2 | B9: 2026-08-17 | C9: 2026-08-18 | D9: T1 | E9: 378 | F9: Constructora del Sur | G9: C4F-912 | H9: Manuel Vega | I9: PREMIUM | J9: 3 | K9: 19.5 | L9: =J9*K9 | M9: Juan P. | N9: FACTURADO | O9: F001-00455
A10: 3 | B10: 2026-08-18 | C10: 2026-08-18 | D10: T2 | E10: 379 | F10: - | G10: - | H10: - | I10: - | J10: 0 | K10: 0 | L10: =J10*K10 | M10: Pedro M. | N10: ANULADO | O10: ERROR LLENADO
A11: 4 | B11: 2026-08-19 | C11: 2026-08-20 | D11: T1 | E11: 380 | F11: Distribuidora Lima | G11: T6U-711 | H11: Jorge Quispe | I11: DIESEL B5 | J11: 10 | K11: 16.8 | L11: =J11*K11 | M11: Luis G. | N11: FACTURADO | O11: F001-00460
A12: 5 | B12: 2026-08-19 | C12: 2026-08-19 | D12: T2 | E12: 381 | F12: Transportes Andina S.A.C. | G12: A1B-823 | H12: Carlos Rojas | I12: PREMIUM | J12: 4 | K12: 19.5 | L12: =J12*K12 | M12: Pedro M. | N12: PENDIENTE | O12: -
A13: 6 | B13: 2026-08-17 | C13: 2026-08-20 | D13: T3 | E13: 382 | F13: Minera Horizonte | G13: V7X-551 | H13: Alonso Ruiz | I13: PREMIUM | J13: 1 | K13: 19.5 | L13: =J13*K13 | M13: Mario S. | N13: PENDIENTE | O13: -
A14: 7 | B14: 2026-08-20 | C14: 2026-08-20 | D14: T1 | E14: 383 | F14: Constructora del Sur | G14: C4F-912 | H14: Manuel Vega | I14: PREMIUM | J14: 4 | K14: 19.5 | L14: =J14*K14 | M14: Juan P. | N14: PENDIENTE | O14: -
A15: 8 | B15: 2026-08-21 | C15: 2026-08-22 | D15: T1 | E15: 384 | F15: Distribuidora Lima | G15: T6U-711 | H15: Jorge Quispe | I15: PREMIUM | J15: 7 | K15: 19.5 | L15: =J15*K15 | M15: Luis G. | N15: PENDIENTE | O15: -
A16: 9 | B16: 2026-08-21 | C16: 2026-08-21 | D16: T2 | E16: 385 | F16: Agropecuaria San José | G16: B8K-102 | H16: Raúl Castro | I16: PREMIUM | J16: 8 | K16: 19.5 | L16: =J16*K16 | M16: Pedro M. | N16: PENDIENTE | O16: -
A17: 10 | B17: 2026-08-22 | C17: 2026-08-22 | D17: T1 | E17: 386 | F17: - | G17: - | H17: - | I17: - | J17: 0 | K17: 0 | L17: =J17*K17 | M17: Juan P. | N17: ANULADO | O17: VALE ROTO
A18: 11 | B18: 2026-08-25 | C18: 2026-08-26 | D18: T1 | E18: 387 | F18: Distribuidora Lima | G18: T6U-711 | H18: Jorge Quispe | I18: DIESEL B5 | J18: 11 | K18: 16.8 | L18: =J18*K18 | M18: Luis G. | N18: PENDIENTE | O18: -
A19: 12 | B19: 2026-08-25 | C19: 2026-08-25 | D19: T2 | E19: 388 | F19: Transportes Andina S.A.C. | G19: A1B-823 | H19: Carlos Rojas | I19: PREMIUM | J19: 4 | K19: 19.5 | L19: =J19*K19 | M19: Pedro M. | N19: PENDIENTE | O19: -
... A27: 20 | B27: 2026-09-02 | C27: 2026-09-02 | D27: T3 | E27: 396 | F27: - | G27: - | H27: - | I27: - | J27: 0 | K27: 0 | L27: =J27*K27 | M27: Mario S. | N27: ANULADO | O27: ERROR EN PLACA
A28: TOTALES GENERALES: | J28: =SUM(J8:J27) | L28: =SUM(L8:L27)

Sheet Kardex Tanques
A1: CONTROL DIARIO DE TANQUES - VARILLAJE Y COMPRAS DE COMBUSTIBLE (KARDEX)
A3: FECHA | B3: PRODUCTO | C3: STOCK INICIAL (GLN) | D3: COMPRAS / CISTERNA | E3: N° GUÍA REMISIÓN | F3: VENTAS CONTÓMETRO | G3: VENTAS VALES | H3: STOCK TEÓRICO (GLN) | I3: STOCK FÍSICO VARILLA | J3: DIFERENCIA / MERMA | K3: OBSERVACIONES
A4: 2026-08-17 | B4: PREMIUM | C4: 1200 | D4: 1500 | E4: GR-002341 | F4: 450 | G4: 11 | H4: =C4+D4-(F4+G4) | I4: 2235 | J4: =I4-H4 | K4: Descarga cisterna 11:00 am
A5: 2026-08-17 | B5: DIESEL B5 | C5: 2500 | D5: 0 | E5: - | F5: 820 | G5: 0 | H5: =C5+D5-(F5+G5) | I5: 1675 | J5: =I5-H5 | K5: Normal
A6: 2026-08-18 | B6: PREMIUM | C6: 2235 | D6: 0 | E6: - | F6: 380 | G6: 0 | H6: =C6+D6-(F6+G6) | I6: 1852 | J6: =I6-H6 | K6: Variación normal
A7: 2026-08-18 | B7: DIESEL B5 | C7: 1675 | D7: 3000 | E7: GR-002358 | F7: 910 | G7: 0 | H7: =C7+D7-(F7+G7) | I7: 3760 | J7: =I7-H7 | K7: Cisterna recibida OK
A8: 2026-08-19 | B8: PREMIUM | C8: 1852 | D8: 0 | E8: - | F8: 410 | G8: 4 | H8: =C8+D8-(F8+G8) | I8: 1435 | J8: =I8-H8 | K8: Normal
A9: 2026-08-19 | B9: DIESEL B5 | C9: 3760 | D9: 0 | E9: - | F9: 980 | G9: 10 | H9: =C9+D9-(F9+G9) | I9: 2768 | J9: =I9-H9 | K9: Normal

Sheet Resumen Clientes
A1: LIQUIDACIÓN DE VALES POR CLIENTE (PENDIENTE DE FACTURAR)
A3: CLIENTE / RAZÓN SOCIAL | B3: CANT. VALES PENDIENTES | C3: GLN DIESEL | D3: GLN PREMIUM | E3: DEUDA TOTAL (S/.) | F3: ESTADO DE CRÉDITO
A4: Transportes Andina S.A.C. | B4: =COUNTIFS('Control de Vales'!E$8:E$100, A4, 'Control de Vales'!M$8:M$100, "PENDIENTE") | C4: =SUMIFS('Control de Vales'!I$8:I$100, 'Control de Vales'!E$8:E$100, A4, 'Control de Vales'!H$8:H$100, "DIESEL B5", 'Control de Vales'!M$8:M$100, "PENDIENTE") | D4: =SUMIFS('Control de Vales'!I$8:I$100, 'Control de Vales'!E$8:E$100, A4, 'Control de Vales'!H$8:H$100, "PREMIUM", 'Control de Vales'!M$8:M$100, "PENDIENTE") | E4: =SUMIFS('Control de Vales'!K$8:K$100, 'Control de Vales'!E$8:E$100, A4, 'Control de Vales'!M$8:M$100, "PENDIENTE") | F4: Activo / Al día
A5: Constructora del Sur | B5: =COUNTIFS('Control de Vales'!E$8:E$100, A5, 'Control de Vales'!M$8:M$100, "PENDIENTE") | C5: =SUMIFS('Control de Vales'!I$8:I$100, 'Control de Vales'!E$8:E$100, A5, 'Control de Vales'!H$8:H$100, "DIESEL B5", 'Control de Vales'!M$8:M$100, "PENDIENTE") | D5: =SUMIFS('Control de Vales'!I$8:I$100, 'Control de Vales'!E$8:E$100, A5, 'Control de Vales'!H$8:H$100, "PREMIUM", 'Control de Vales'!M$8:M$100, "PENDIENTE") | E5: =SUMIFS('Control de Vales'!K$8:K$100, 'Control de Vales'!E$8:E$100, A5, 'Control de Vales'!M$8:M$100, "PENDIENTE") | F5: Activo / Al día
A6: Distribuidora Lima | B6: =COUNTIFS('Control de Vales'!E$8:E$100, A6, 'Control de Vales'!M$8:M$100, "PENDIENTE") | C6: =SUMIFS('Control de Vales'!I$8:I$100, 'Control de Vales'!E$8:E$100, A6, 'Control de Vales'!H$8:H$100, "DIESEL B5", 'Control de Vales'!M$8:M$100, "PENDIENTE") | D6: =SUMIFS('Control de Vales'!I$8:I$100, 'Control de Vales'!E$8:E$100, A6, 'Control de Vales'!H$8:H$100, "PREMIUM", 'Control de Vales'!M$8:M$100, "PENDIENTE") | E6: =SUMIFS('Control de Vales'!K$8:K$100, 'Control de Vales'!E$8:E$100, A6, 'Control de Vales'!M$8:M$100, "PENDIENTE") | F6: Por facturar fin de mes
A7: Agropecuaria San José | B7: =COUNTIFS('Control de Vales'!E$8:E$100, A7, 'Control de Vales'!M$8:M$100, "PENDIENTE") | C7: =SUMIFS('Control de Vales'!I$8:I$100, 'Control de Vales'!E$8:E$100, A7, 'Control de Vales'!H$8:H$100, "DIESEL B5", 'Control de Vales'!M$8:M$100, "PENDIENTE") | D7: =SUMIFS('Control de Vales'!I$8:I$100, 'Control de Vales'!E$8:E$100, A7, 'Control de Vales'!H$8:H$100, "PREMIUM", 'Control de Vales'!M$8:M$100, "PENDIENTE") | E7: =SUMIFS('Control de Vales'!K$8:K$100, 'Control de Vales'!E$8:E$100, A7, 'Control de Vales'!M$8:M$100, "PENDIENTE") | F7: Activo / Al día
A8: Minera Horizonte | B8: =COUNTIFS('Control de Vales'!E$8:E$100, A8, 'Control de Vales'!M$8:M$100, "PENDIENTE") | C8: =SUMIFS('Control de Vales'!I$8:I$100, 'Control de Vales'!E$8:E$100, A8, 'Control de Vales'!H$8:H$100, "DIESEL B5", 'Control de Vales'!M$8:M$100, "PENDIENTE") | D8: =SUMIFS('Control de Vales'!I$8:I$100, 'Control de Vales'!E$8:E$100, A8, 'Control de Vales'!H$8:H$100, "PREMIUM", 'Control de Vales'!M$8:M$100, "PENDIENTE") | E8: =SUMIFS('Control de Vales'!K$8:K$100, 'Control de Vales'!E$8:E$100, A8, 'Control de Vales'!M$8:M$100, "PENDIENTE") | F8: Por facturar fin de mes
